binary_gentoo/__init__.py
binary_gentoo/internal/__init__.py
binary_gentoo/internal/atoms.py
binary_gentoo/internal/fs_lock.py
binary_gentoo/internal/json_formatter.py
binary_gentoo/internal/priority_queue.py
binary_gentoo/internal/reporter.py
binary_gentoo/internal/version.py
binary_gentoo/internal/cli/__init__.py
binary_gentoo/internal/cli/_distro.py
binary_gentoo/internal/cli/_enrich.py
binary_gentoo/internal/cli/_parser.py
binary_gentoo/internal/cli/build.py
binary_gentoo/internal/cli/clean.py
binary_gentoo/internal/cli/local_queue.py
binary_gentoo/internal/cli/packages.py
binary_gentoo/internal/cli/tree_diff.py
binary_gentoo/internal/cli/tree_sync.py
binary_gentoo/internal/cli/tests/__init__.py
binary_gentoo/internal/cli/tests/test__enrich.py
binary_gentoo/internal/cli/tests/test_build.py
binary_gentoo/internal/cli/tests/test_clean.py
binary_gentoo/internal/cli/tests/test_local_queue.py
binary_gentoo/internal/cli/tests/test_packages.py
binary_gentoo/internal/cli/tests/test_tree_diff.py
binary_gentoo/internal/cli/tests/test_tree_sync.py
binary_gentoo/internal/tests/__init__.py
binary_gentoo/internal/tests/test_atoms.py
binary_gentoo/internal/tests/test_json_formatter.py
binary_gentoo/internal/tests/test_priority_queue.py
binary_gentoo/internal/tests/test_reporter.py
binary_gentoo-7.0.1.dist-info/licenses/COPYING
binary_gentoo-7.0.1.dist-info/METADATA
binary_gentoo-7.0.1.dist-info/WHEEL
binary_gentoo-7.0.1.dist-info/entry_points.txt
binary_gentoo-7.0.1.dist-info/top_level.txt
binary_gentoo-7.0.1.dist-info/RECORD
