Metadata-Version: 2.4
Name: binary-gentoo
Version: 7.0.1
Summary: CLI tools to build Gentoo packages on a non-Gentoo Linux host
Home-page: https://github.com/hartwork/binary-gentoo
Author: Sebastian Pipping
Author-email: sebastian@pipping.org
License: AGPLv3+
Classifier: Programming Language :: Python
Classifier: Programming Language :: Python :: 3
Classifier: Programming Language :: Python :: 3.9
Classifier: Programming Language :: Python :: 3.10
Classifier: Programming Language :: Python :: 3.11
Classifier: Programming Language :: Python :: 3.12
Classifier: Programming Language :: Python :: 3.13
Classifier: Programming Language :: Python :: 3 :: Only
Requires-Python: >=3.9
License-File: COPYING
Requires-Dist: PyYAML
Provides-Extra: ci
Requires-Dist: coverage; extra == "ci"
Requires-Dist: pytest; extra == "ci"
Provides-Extra: tests
Requires-Dist: freezegun; extra == "tests"
Requires-Dist: parameterized; extra == "tests"
Dynamic: author
Dynamic: author-email
Dynamic: classifier
Dynamic: description
Dynamic: description-content-type
Dynamic: home-page
Dynamic: license
Dynamic: license-file
Dynamic: provides-extra
Dynamic: requires-dist
Dynamic: requires-python
Dynamic: summary
